[
  {
    "name": "Winged Hive Tyrant",
    "points": [195],
    "stats": {
      "movement": 12,
      "toughness": 9,
      "save": 2,
      "invulnerable": 4,
      "wounds": 10,
      "leadership": 7,
      "objective_control": 3
    },
    "weapons": [
      {
        "name": "Heavy Venom Cannon",
        "range": 36,
        "attacks": 0,
        "attack_dice": "d3",
        "hit": 2,
        "strength": 9,
        "armour_pen": 2,
        "damage": 3,
        "tags": ["Blast"],
        "ranged": true
      },
      {
        "name": "Stranglethorn Cannon",
        "range": 36,
        "attacks": 1,
        "attack_dice": "d6",
        "hit": 2,
        "strength": 7,
        "armour_pen": 1,
        "damage": 2,
        "tags": ["Blast"],
        "ranged": true
      },
      {
        "name": "Monstrous Bonesword and Lash Whip",
        "range": 0,
        "attacks": 6,
        "hit": 2,
        "strength": 9,
        "armour_pen": 2,
        "damage": 3,
        "tags": ["Twin-Linked"],
        "ranged": false
      },
      {
        "name": "Monstrous Scything Talons",
        "range": 0,
        "attacks": 4,
        "hit": 2,
        "strength": 7,
        "armour_pen": 2,
        "damage": 2,
        "tags": ["Extra Attacks"],
        "ranged": false
      },
      {
        "name": "Tyrant Talons",
        "range": 0,
        "attacks": 5,
        "hit": 2,
        "strength": 7,
        "armour_pen": 2,
        "damage": 2,
        "tags": [],
        "ranged": false
      }
    ],
    "abilities": {
      "Core": ["Deadly Demise D3", "Deep Strike"],
      "Will of the Hive Mind": "Once per turn, one friendly Tyranids unit within 12 inches of one or more models with this ability can be targeted with a Stratagem for 0CP, even if another unit from your army has already been targeted with that Stratagem this phase.",
      "Paroxysm [Psychic]": "At the start of the Fight phase, you can select one enemy unit within 12 inches of and visible to this model and roll one D6: on a 1, this Psyker suffers D3 mortal wounds; on a 2+, until the end of the phase, subtract 1 from the Attacks characteristic of weapons equipped by models in that unit.",
      "Shadow in the Warp": "If your Army Faction is Tyranids, once per battle, in either player’s Command phase, if one or more units from your army with this ability are on the battlefield, you can unleash the Shadow in the Warp. When you do, each enemy unit on the battlefield must take a Battle-shock test.",
      "synapse": true
    },
    "tags": [
      "Monster",
      "Character",
      "Psyker",
      "Great Devourer",
      "Synapse",
      "Winged Hive Tyrant",
      "Tyranids"
    ],
    "models": {
      "Winged Hive Tyrant": [1]
    },
    "equipment": ["Monstrous Bonesword and Lash Whip", "Tyrant Talons"]
  },

  {
    "name": "Hive Tyrant",
    "points": [220],
    "stats": {
      "movement": 8,
      "toughness": 10,
      "save": 2,
      "invulnerable": 4,
      "wounds": 10,
      "leadership": 7,
      "objective_control": 3
    },
    "weapons": [
      {
        "name": "Heavy Venom Cannon",
        "range": 36,
        "attacks": 0,
        "attack_dice": "d3",
        "hit": 2,
        "strength": 9,
        "armour_pen": 2,
        "damage": 3,
        "tags": ["Blast"],
        "ranged": true
      },
      {
        "name": "Stranglethorn Cannon",
        "range": 36,
        "attacks": 1,
        "attack_dice": "d6",
        "hit": 2,
        "strength": 7,
        "armour_pen": 1,
        "damage": 2,
        "tags": ["Blast"],
        "ranged": true
      },
      {
        "name": "Monstrous Bonesword and Lash Whip",
        "range": 0,
        "attacks": 6,
        "hit": 2,
        "strength": 9,
        "armour_pen": 2,
        "damage": 3,
        "tags": ["Twin-Linked"],
        "ranged": false
      },
      {
        "name": "Monstrous Scything Talons",
        "range": 0,
        "attacks": 4,
        "hit": 2,
        "strength": 7,
        "armour_pen": 2,
        "damage": 2,
        "tags": ["Extra Attacks"],
        "ranged": false
      }
    ],
    "abilities": {
      "Core": ["Deadly Demise D3", "leader"],
      "Will of the Hive Mind": "Once per turn, one friendly Tyranids unit within 12 inches of one or more models with this ability can be targeted with a Stratagem for 0CP, even if another unit from your army has already been targeted with that Stratagem this phase.",
      "Onslaught [Aura, Psychic]": "While a friendly Tyranids unit is within 6 inches of this model, ranged weapons equipped by models in that unit have the [ASSAULT] ability.",
      "leader": ["Tyrant Guard"],
      "Shadow in the Warp": "If your Army Faction is Tyranids, once per battle, in either player’s Command phase, if one or more units from your army with this ability are on the battlefield, you can unleash the Shadow in the Warp. When you do, each enemy unit on the battlefield must take a Battle-shock test.",
      "synapse": true
    },
    "tags": [
      "Monster",
      "Character",
      "Psyker",
      "Great Devourer",
      "Synapse",
      "Hive Tyrant"
    ],
    "models": {
      "Hive Tyrant": [1]
    },
    "equipment": [
      "Monstrous Bonesword and Lash Whip",
      "Monstrous Scything Talons"
    ]
  },

  {
    "name": "Swarmlord",
    "points": [250],
    "stats": {
      "movement": 8,
      "toughness": 10,
      "save": 2,
      "invulnerable": 4,
      "wounds": 10,
      "leadership": 7,
      "objective_control": 3
    },
    "weapons": [
      {
        "name": "Synaptic Pulse",
        "range": 18,
        "attacks": 6,
        "hit": 0,
        "strength": 5,
        "armour_pen": 1,
        "damage": 2,
        "tags": ["Psychic", "Torrent"],
        "ranged": true
      },
      {
        "name": "Bone Sabres",
        "range": 0,
        "attacks": 4,
        "hit": 2,
        "strength": 9,
        "armour_pen": 2,
        "damage": 3,
        "tags": ["Twin-Linked"],
        "ranged": false
      }
    ],
    "abilities": {
      "Core": ["Deadly Demise D3", "leader"],
      "leader": ["Tyrant Guard"],
      "Shadow in the Warp": "If your Army Faction is Tyranids, once per battle, in either player’s Command phase, if one or more units from your army with this ability are on the battlefield, you can unleash the Shadow in the Warp. When you do, each enemy unit on the battlefield must take a Battle-shock test.",
      "Hive Commander": "At the start of your Command phase, if this model is on the battlefield, you gain 1CP.",
      "Malign Presence": "Once per battle, after your opponent uses a Stratagem, if this model is your Warlord and is on the battlefield, it can use this ability. If it does, until the end of the battle, increase that Stratagem’s cost to your opponent by 1CP.",
      "Domination of the Hive Mind": "While a friendly Tyranids unit is within 9 inches of this model, that unit is within your army’s Synapse Range.",
      "synapse": true
    },
    "tags": [
      "Monster",
      "Character",
      "Epic Hero",
      "Psyker",
      "Great Devourer",
      "Synapse",
      "The Swarmlord"
    ],
    "models": {
      "Swarmlord": [1]
    },
    "equipment": ["Synaptic Pulse", "Bone Sabres"]
  },

  {
    "name": "Broodlord",
    "points": [100],
    "stats": {
      "movement": 8,
      "toughness": 5,
      "save": 4,
      "invulnerable": 4,
      "wounds": 6,
      "leadership": 7,
      "objective_control": 1
    },
    "weapons": [
      {
        "name": "Broodlord Claws and Talons",
        "range": 0,
        "attacks": 5,
        "hit": 2,
        "strength": 6,
        "armour_pen": 2,
        "damage": 2,
        "tags": ["Devastating Wounds", "Twin-Linked"],
        "ranged": false
      }
    ],
    "abilities": {
      "leader": ["Genestealers"],
      "Core": ["Scouts 8 inches", "leader"],
      "synapse": true,
      "Vicious Insight": "While this model is leading a unit, weapons equipped by models in that unit have the [DEVASTATING WOUNDS] ability.",
      "Hypnosic Gaze [Psychic]": "At the start of the Fight phase, select one enemy unit within Engagement Range of this model. Until the end of the phase, each time a model in that unit makes an attack, subtract 1 from the Hit roll."
    },
    "tags": ["Infantry", "Character", "Psyker", "Great Devourer", "Broodlord"],
    "models": {
      "Broodlord": [1]
    },
    "equipment": ["Broodlord Claws and Talons"]
  },

  {
    "name": "Winged Tyranid Prime",
    "points": [80],
    "stats": {
      "movement": 12,
      "toughness": 5,
      "save": 4,
      "invulnerable": 7,
      "wounds": 6,
      "leadership": 7,
      "objective_control": 1
    },
    "weapons": [
      {
        "name": "Prime Talons",
        "range": 0,
        "attacks": 6,
        "hit": 2,
        "strength": 6,
        "armour_pen": 1,
        "damage": 2,
        "tags": [],
        "ranged": false
      }
    ],
    "abilities": {
      "Core": ["Deep Strike", "leader"],
      "leader": [
        "Tyranid Warriors with Melee Bio-Weapons",
        "Tyranid Warriors with Ranged Bio-weapons"
      ],
      "Alpha Warrior": "While this model is leading a unit, weapons equipped by models in that unit have the [SUSTAINED HITS 1] ability",
      "Death Blow": "If this model is destroyed by a melee attack, if it has not fought this phase, roll one D6: on a 4+, do not remove it from play. The destroyed model can fight after the attacking model’s unit has finished making its attacks, and is then removed from play.",
      "Shadow in the Warp": "If your Army Faction is Tyranids, once per battle, in either player’s Command phase, if one or more units from your army with this ability are on the battlefield, you can unleash the Shadow in the Warp. When you do, each enemy unit on the battlefield must take a Battle-shock test.",
      "synapse": true
    },
    "tags": [
      "Infantry",
      "Character",
      "fly",
      "Great Devourer",
      "Synapse",
      "Winged Tyranid Prime"
    ],
    "models": {
      "Broodlord": [1]
    },
    "equipment": ["Prime Talons"]
  },

  {
    "name": "Tervigon",
    "points": [200],
    "stats": {
      "movement": 8,
      "toughness": 11,
      "save": 2,
      "invulnerable": 7,
      "wounds": 16,
      "leadership": 7,
      "objective_control": 5
    },
    "weapons": [
      {
        "name": "Stinger salvoes",
        "range": 24,
        "attacks": 8,
        "hit": 3,
        "strength": 5,
        "armour_pen": 0,
        "damage": 1,
        "tags": [],
        "ranged": true
      },
      {
        "name": "Massive crushing claws",
        "range": 0,
        "attacks": 4,
        "hit": 4,
        "strength": 12,
        "armour_pen": 3,
        "damage": 1,
        "damage_dice": "d6",
        "tags": [],
        "ranged": false
      },
      {
        "name": "Massive scything talons - strike",
        "range": 0,
        "attacks": 4,
        "hit": 3,
        "strength": 9,
        "armour_pen": 2,
        "damage": 0,
        "damage_dice": "d6",
        "tags": [],
        "ranged": false
      },
      {
        "name": "Massive scything talons - sweep",
        "range": 0,
        "attacks": 8,
        "hit": 3,
        "strength": 9,
        "armour_pen": 2,
        "damage": 2,
        "tags": [],
        "ranged": false
      }
    ],
    "abilities": {
      "Core": ["Deadly Demise D6"],
      "Shadow in the Warp": "If your Army Faction is Tyranids, once per battle, in either player’s Command phase, if one or more units from your army with this ability are on the battlefield, you can unleash the Shadow in the Warp. When you do, each enemy unit on the battlefield must take a Battle-shock test.",
      "synapse": true,
      "Spawn Termagants": "In your Command phase, you can select one friendly Termagants unit within 6 inches of this model and return up to D3+3 destroyed Termagant models to that unit. A Termagants unit cannot be selected for this ability more than once per phase.",
      "Brood Progenitor [Aura, Psychic]": "While a friendly Termagants unit is within 6 inches of this model, ranged weapons equipped by models in that unit have the [LETHAL HITS] ability.",
      "Damaged": "While this model has 1-5 wounds remaining, each time this model makes an attack, subtract 1 from the Hit roll."
    },
    "tags": [
      "Monster",
      "Character",
      "Psyker",
      "Great Devourer",
      "Synapse",
      "Tervigon"
    ],
    "models": {
      "Tervigon": [1]
    },
    "equipment": ["Stinger salvoes", "Massive scything talons"]
  },

  {
    "name": "Old One Eye",
    "points": [140],
    "stats": {
      "movement": 8,
      "toughness": 9,
      "save": 2,
      "invulnerable": 7,
      "wounds": 9,
      "leadership": 8,
      "objective_control": 3
    },
    "weapons": [
      {
        "name": "Old One Eye's claws and talons - strike",
        "range": 0,
        "attacks": 6,
        "hit": 3,
        "strength": 14,
        "armour_pen": 3,
        "damage": 1,
        "damage_dice": "d6",
        "tags": [],
        "ranged": false
      },
      {
        "name": "Old One Eye's claws and talons - sweep",
        "range": 0,
        "attacks": 12,
        "hit": 3,
        "strength": 6,
        "armour_pen": 1,
        "damage": 1,
        "tags": [],
        "ranged": false
      }
    ],
    "abilities": {
      "Core": ["Feel No Pain 5+", "leader"],
      "Shadow in the Warp": "If your Army Faction is Tyranids, once per battle, in either player’s Command phase, if one or more units from your army with this ability are on the battlefield, you can unleash the Shadow in the Warp. When you do, each enemy unit on the battlefield must take a Battle-shock test.",
      "synapse": true,
      "leader": ["Carnifexes"],
      "Alpha Leader": "While this model is leading a unit, each time a model in that unit makes an attack, you can re-roll the Hit roll.",
      "Unstoppable Monster": "At the start of each player’s Command phase, this model regains up to D3 lost wounds."
    },
    "tags": [
      "Monster",
      "Character",
      "Epic Hero",
      "Great Devourer",
      "Old One Eye"
    ],
    "models": {
      "Old One Eye": [1]
    },
    "equipment": [
      "Old One Eye's claws and talons - strike",
      "Old One Eye's claws and talons - sweep"
    ]
  },

  {
    "name": "Tyranid Warriors with Ranged Bio-Weapons",
    "points": [70, 180],
    "stats": {
      "movement": 6,
      "toughness": 5,
      "save": 4,
      "invulnerable": 7,
      "wounds": 3,
      "leadership": 7,
      "objective_control": 2
    },
    "weapons": [
      {
        "name": "Barbed Strangler",
        "range": 36,
        "attacks": 1,
        "attack_dice": "d6",
        "hit": 4,
        "strength": 6,
        "armour_pen": 1,
        "damage": 1,
        "tags": ["Blast"],
        "ranged": true
      },
      {
        "name": "Deathspitter",
        "range": 24,
        "attacks": 3,
        "hit": 4,
        "strength": 5,
        "armour_pen": 1,
        "damage": 1,
        "tags": [],
        "ranged": true
      },
      {
        "name": "Devourer",
        "range": 18,
        "attacks": 5,
        "hit": 4,
        "strength": 4,
        "armour_pen": 0,
        "damage": 1,
        "tags": [],
        "ranged": true
      },
      {
        "name": "Spinefists",
        "range": 12,
        "attacks": 2,
        "hit": 4,
        "strength": 4,
        "armour_pen": 0,
        "damage": 1,
        "tags": ["Assault", "Pistol", "Twin-Linked"],
        "ranged": true
      },
      {
        "name": "Venom Cannon",
        "range": 36,
        "attacks": 0,
        "attack_dice": "d3",
        "hit": 4,
        "strength": 9,
        "armour_pen": 2,
        "damage": 2,
        "tags": ["Blast"],
        "ranged": true
      },
      {
        "name": "Bio-weapons",
        "range": 0,
        "attacks": 5,
        "hit": 3,
        "strength": 5,
        "armour_pen": 1,
        "damage": 1,
        "tags": [],
        "ranged": false
      }
    ],
    "abilities": {
      "Shadow in the Warp": "If your Army Faction is Tyranids, once per battle, in either player’s Command phase, if one or more units from your army with this ability are on the battlefield, you can unleash the Shadow in the Warp. When you do, each enemy unit on the battlefield must take a Battle-shock test.",
      "synapse": true,
      "Adaptable Predators": "This unit is eligible to shoot and declare a charge in a turn in which it Fell Back."
    },
    "tags": ["Infantry", "Synapse", "Tyranid Warriors with Ranged Bio-Weapons"],
    "models": {
      "Tyranid Warriors with Ranged Bio-Weapons": [3, 6]
    },
    "equipment": ["Devourer", "Bio-weapons"]
  },

  {
    "name": "Tyranid Warriors with Melee Bio-Weapons",
    "points": [90, 180],
    "stats": {
      "movement": 6,
      "toughness": 5,
      "save": 4,
      "invulnerable": 7,
      "wounds": 3,
      "leadership": 7,
      "objective_control": 2
    },
    "weapons": [
      {
        "name": "Bio-weapons",
        "range": 0,
        "attacks": 5,
        "hit": 3,
        "strength": 5,
        "armour_pen": 1,
        "damage": 1,
        "tags": ["Twin-Linked"],
        "ranged": false
      }
    ],
    "abilities": {
      "Shadow in the Warp": "If your Army Faction is Tyranids, once per battle, in either player’s Command phase, if one or more units from your army with this ability are on the battlefield, you can unleash the Shadow in the Warp. When you do, each enemy unit on the battlefield must take a Battle-shock test.",
      "synapse": true,
      "Adredalised Onslaught": "At the start of the Fight phase, you can select one of the following abilities to apply to models in this unit until the end of the phase: 1 - Aggression Imperative: Each time a model in this unit makes a melee attack, re-roll a Hit roll of 1. 2 - Preservation Imperative: Each time a saving throw is made for a model in this unit, re-roll a saving throw of 1."
    },
    "tags": ["Infantry", "Synapse", "Tyranid Warriors with Melee Bio-Weapons"],
    "models": {
      "Tyranid Warriors with Melee Bio-Weapons": [3, 6]
    },
    "equipment": ["Bio-weapons"]
  },

  {
    "name": "Termagants",
    "points": [60, 120],
    "stats": {
      "movement": 6,
      "toughness": 3,
      "save": 5,
      "invulnerable": 7,
      "wounds": 1,
      "leadership": 8,
      "objective_control": 2
    },
    "weapons": [
      {
        "name": "Fleshborer",
        "range": 18,
        "attacks": 1,
        "hit": 4,
        "strength": 5,
        "armour_pen": 0,
        "damage": 1,
        "tags": ["Assault"],
        "ranged": true
      },
      {
        "name": "Termagant Spinefist",
        "range": 12,
        "attacks": 2,
        "hit": 4,
        "strength": 3,
        "armour_pen": 0,
        "damage": 1,
        "tags": ["Assault", "Pistol", "Twin-Linked"],
        "ranged": true
      },
      {
        "name": "Termagant Devourer",
        "range": 18,
        "attacks": 2,
        "hit": 4,
        "strength": 4,
        "armour_pen": 0,
        "damage": 1,
        "tags": [],
        "ranged": true
      },
      {
        "name": "Xenos claws and teeth",
        "range": 0,
        "attacks": 1,
        "hit": 4,
        "strength": 3,
        "armour_pen": 0,
        "damage": 1,
        "tags": [],
        "ranged": false
      }
    ],
    "abilities": {
      "synapse": false,
      "Skulking Horrors": "Once per turn, when an enemy unit ends a normal, Advance or Fall Back move within 9 inches of this unit, if this unit is not within Engagement Range of one or more enemy units, it can make a Normal move of up to D6 inches."
    },
    "tags": [
      "Infantry",
      "Termagants",
      "Great Devourer",
      "Endless Multitude",
      "Battleline"
    ],
    "models": {
      "Termagants": [10, 20]
    },
    "equipment": ["Fleshborer", "Xenos claws and teeth"]
  },

  {
    "name": "Hermagaunts",
    "points": [10, 20],
    "stats": {
      "movement": 10,
      "toughness": 3,
      "save": 5,
      "invulnerable": 7,
      "wounds": 1,
      "leadership": 8,
      "objective_control": 2
    },
    "weapons": [
      {
        "name": "Hormagaunt talons",
        "range": 0,
        "attacks": 3,
        "hit": 4,
        "strength": 3,
        "armour_pen": 1,
        "damage": 1,
        "tags": [],
        "ranged": true
      }
    ],
    "abilities": {
      "synapse": false,
      "Bounding Leap": "This unit is eligible to declare a charge in a turn in which it Advanced."
    },
    "tags": [
      "Infantry",
      "Battleline",
      "Great Devourer",
      "Endless Multitude",
      "Hormagaunts"
    ],
    "models": {
      "Termagants": [10, 20]
    },
    "equipment": ["Hormagaunt talons"]
  },

  {
    "name": "Gargoyles",
    "points": [75, 150],
    "stats": {
      "movement": 12,
      "toughness": 3,
      "save": 6,
      "invulnerable": 7,
      "wounds": 1,
      "leadership": 8,
      "objective_control": 2
    },
    "weapons": [
      {
        "name": "Fleshborer",
        "range": 18,
        "attacks": 1,
        "hit": 4,
        "strength": 5,
        "armour_pen": 0,
        "damage": 1,
        "tags": ["Assault"],
        "ranged": true
      },
      {
        "name": "Blinding Venom",
        "range": 0,
        "attacks": 1,
        "hit": 4,
        "strength": 3,
        "armour_pen": 0,
        "damage": 1,
        "tags": [],
        "ranged": false
      }
    ],
    "abilities": {
      "Core": ["Deep Strike"],
      "synapse": false,
      "Winged Swarm": "In your Shooting phase, after this unit has shot, if it is not within Engagement Range of any enemy units, it can make a Normal move of up to 6 inches. If it does, until the end of the turn, this unit is not eligible to declare a charge."
    },
    "tags": [
      "Infantry",
      "Battleline",
      "fly",
      "Great Devourer",
      "Endless Multitude",
      "Gargoyles"
    ],
    "models": {
      "Termagants": [10, 20]
    },
    "equipment": ["Fleshborer", "Blinding Venom"]
  },

  {
    "name": "Toxicrene",
    "points": [200],
    "stats": {
      "movement": 8,
      "toughness": 11,
      "save": 3,
      "invulnerable": 7,
      "wounds": 14,
      "leadership": 8,
      "objective_control": 4
    },
    "weapons": [
      {
        "name": "Massive Toxic Lashes - ranged",
        "range": 9,
        "attacks": 0,
        "attacks_dice": "2d6",
        "hit": 3,
        "strength": 6,
        "armour_pen": 1,
        "damage": 2,
        "tags": ["Anti-Infantry 2+"],
        "ranged": true
      },
      {
        "name": "Massive Toxic Lashes - melee",
        "range": 0,
        "attacks": 12,
        "hit": 3,
        "strength": 6,
        "armour_pen": 1,
        "damage": 2,
        "tags": ["Anti-Infantry 2+"],
        "ranged": false
      }
    ],
    "abilities": {
      "Core": ["Deadly Demise D3"],
      "synapse": true,
      "Grasping Tendrils": "Each time an enemy unit (excluding Titanic units) within Engagement Range of one or more units from your army with this ability is selected to Fall Back, you can roll one D6: on a 3+, that enemy unit must Remain Stationary instead.",
      "Hypertoxic Miasma [Aura]": "At the end of your Movement phase, roll one D6 for each enemy unit within 6 inches of this model: on a 2-3, that unit suffers 1 mortal wound; on a 4-5, that unit suffers D3 mortal wounds; on a 6, that unit suffers D6 mortal wounds.",
      "Damaged": "While this model has 1-5 wounds remaining, each time this model makes an attack, subtract 1 from the Hit roll."
    },
    "tags": ["Monster", "Great Devourer", "Toxicrene", "Tyranids"],
    "models": {
      "Toxicrene": [1, 1]
    },
    "equipment": [
      "Massive Toxic Lashes - ranged",
      "Massive Toxic Lashes - melee"
    ]
  },

  {
    "name": "Tyrant Guard",
    "points": [95, 190],
    "stats": {
      "movement": 6,
      "toughness": 8,
      "save": 3,
      "invulnerable": 7,
      "wounds": 4,
      "leadership": 8,
      "objective_control": 1
    },
    "weapons": [
      {
        "name": "Bone Cleaver, Lash Whip and Rending Claws",
        "range": 0,
        "attacks": 3,
        "hit": 3,
        "strength": 5,
        "armour_pen": 1,
        "damage": 2,
        "tags": ["Twin-Linked"],
        "ranged": false
      },
      {
        "name": "Crushing Claws and Rending Claws",
        "range": 0,
        "attacks": 3,
        "hit": 4,
        "strength": 8,
        "armour_pen": 2,
        "damage": 2,
        "tags": [],
        "ranged": false
      },
      {
        "name": "Scything Talons and Rending Claws",
        "range": 0,
        "attacks": 5,
        "hit": 3,
        "strength": 5,
        "armour_pen": 1,
        "damage": 1,
        "tags": [],
        "ranged": false
      }
    ],
    "abilities": {
      "synapse": true,
      "Guardian Organism": "While a Character model is leading this unit, that Character has the Feel No Pain 5+ ability."
    },
    "tags": ["Infantry", "Great Devourer", "Tyrant Guard", "Tyranids"],
    "models": {
      "Tyrant Guard": [3, 6]
    },
    "equipment": ["Scything Talons and Rending Claws"]
  },

  {
    "name": "Neurotyrant",
    "points": [105],
    "stats": {
      "movement": 6,
      "toughness": 8,
      "save": 4,
      "invulnerable": 4,
      "wounds": 9,
      "leadership": 7,
      "objective_control": 3
    },
    "weapons": [
      {
        "name": "Psychic Scream",
        "range": 18,
        "attacks": 0,
        "attacks_dice": "2d6",
        "hit": 0,
        "strength": 5,
        "armour_pen": 1,
        "damage": 2,
        "tags": ["Ignores Cover", "Psychic", "Torrent"],
        "ranged": true
      },
      {
        "name": "Neurotyrant Claws and Lashes",
        "range": 0,
        "attacks": 6,
        "hit": 3,
        "strength": 5,
        "armour_pen": 0,
        "damage": 1,
        "tags": [],
        "ranged": false
      }
    ],
    "abilities": {
      "Core": ["leader"],
      "synapse": true,
      "leader": ["Neurogaunts", "Tyrant Guard"],
      "Shadow in the Warp": "If your Army Faction is Tyranids, once per battle, in either player’s Command phase, if one or more units from your army with this ability are on the battlefield, you can unleash the Shadow in the Warp. When you do, each enemy unit on the battlefield must take a Battle-shock test.",
      "Node Lash [Psychic]": "While this model is leading a unit, each time a model in that unit makes an attack, add 1 to the Hit roll. If the target is Battle-shocked, add 1 to the Wound roll as well.",
      "Psychic Terror [Psychic]": "If one or more Neurotyrants from your army are on the battlefield when you unleash the Shadow in the Warp, subtract 1 from the Battle-shock test each enemy unit on the battlefield must take as a result.",
      "Synaptic Relays": "In your Command phase, you can select up to two friendly Tyranids units within 12 inches of this model’s unit. Until the start of your next Command phase, the selected units are always considered to be within Synapse Range of your army."
    },
    "tags": [
      "Monster",
      "Character",
      "fly",
      "Psyker",
      "Great Devourer",
      "Synapse",
      "Neurotyrant",
      "Tyranids"
    ],
    "models": {
      "Neurotyrant": [1, 1]
    },
    "equipment": ["Psychic Scream", "Neurotyrant Claws and Lashes"]
  },

  {
    "name": "Lictor",
    "points": [75],
    "stats": {
      "movement": 8,
      "toughness": 6,
      "save": 4,
      "invulnerable": 5,
      "wounds": 6,
      "leadership": 7,
      "objective_control": 1
    },
    "weapons": [
      {
        "name": "Lictor Claws and Talons",
        "range": 0,
        "attacks": 6,
        "hit": 2,
        "strength": 7,
        "armour_pen": 2,
        "damage": 2,
        "tags": ["Precision"],
        "ranged": false
      }
    ],
    "abilities": {
      "Core": ["Fights First", "Infiltrators", "Lone Operative", "Stealth"],
      "synapse": false,
      "Feeder Tendrils": "Each time this model destroys an enemy Character model, you gain 1CP.",
      "Pheromone Trail": "Once per battle round, you can target one model with this ability with the Rapid Ingress Stratagem for 0CP."
    },
    "tags": ["Infantry", "Great Devourer", "Lictor", "Tyranids"],
    "models": {
      "Lictor": [1, 1]
    },
    "equipment": ["Lictor Claws and Talons"]
  },

  {
    "name": "Deathleaper",
    "points": [80],
    "stats": {
      "movement": 8,
      "toughness": 6,
      "save": 4,
      "invulnerable": 4,
      "wounds": 7,
      "leadership": 7,
      "objective_control": 1
    },
    "weapons": [
      {
        "name": "Lictor Claws and Talons",
        "range": 0,
        "attacks": 6,
        "hit": 2,
        "strength": 7,
        "armour_pen": 2,
        "damage": 2,
        "tags": ["Precision"],
        "ranged": false
      }
    ],
    "abilities": {
      "Core": ["Fights First", "Infiltrators", "Lone Operative", "Stealth"],
      "synapse": false,
      "Feeder Tendrils": "Each time this model destroys an enemy Character model, you gain 1CP.",
      "Pheromone Trail": "Once per battle round, you can target one model with this ability with the Rapid Ingress Stratagem for 0CP."
    },
    "tags": ["Infantry", "Great Devourer", "Neurotyrant", "Tyranids"],
    "models": {
      "Deathleaper": [1, 1]
    },
    "equipment": ["Lictor Claws and Talons"]
  },

  {
    "name": "Maleceptor",
    "points": [165],
    "stats": {
      "movement": 8,
      "toughness": 11,
      "save": 3,
      "invulnerable": 4,
      "wounds": 14,
      "leadership": 7,
      "objective_control": 4
    },
    "weapons": [
      {
        "name": "Psychic Overload",
        "range": 18,
        "attacks": 3,
        "attacks_dice": "1d6",
        "hit": 3,
        "strength": 10,
        "armour_pen": 2,
        "damage": 3,
        "tags": ["Blast", "Psychic"],
        "ranged": true
      },
      {
        "name": "Massive scything talons - strike",
        "range": 0,
        "attacks": 3,
        "hit": 3,
        "strength": 9,
        "armour_pen": 2,
        "damage": 1,
        "damage_dice": "d6",
        "tags": [],
        "ranged": false
      },
      {
        "name": "Massive scything talons - sweep",
        "range": 0,
        "attacks": 6,
        "hit": 3,
        "strength": 7,
        "armour_pen": 1,
        "damage": 2,
        "tags": [],
        "ranged": false
      }
    ],
    "abilities": {
      "Core": ["Deadly Demise D3"],
      "synapse": false,
      "Shadow in the Warp": "If your Army Faction is Tyranids, once per battle, in either player’s Command phase, if one or more units from your army with this ability are on the battlefield, you can unleash the Shadow in the Warp. When you do, each enemy unit on the battlefield must take a Battle-shock test.",
      "Encephalic Diffusion [Aura, Psychic]": "While an enemy unit is within 6 inches of this model, each time a model in that unit makes an attack, subtract 1 from the Hit roll, and, if that enemy unit is Below Half-strength, subtract 1 from the Wound roll as well.",
      "Damaged": "While this model has 1-5 wounds remaining, each time this model makes an attack, subtract 1 from the Hit roll.",
      "Feeder Tendrils": "Each time this model destroys an enemy Character model, you gain 1CP.",
      "Pheromone Trail": "Once per battle round, you can target one model with this ability with the Rapid Ingress Stratagem for 0CP."
    },
    "tags": [
      "Monster",
      "Psyker",
      "Great Devourer",
      "Synapse",
      "Maleceptor",
      "Tyranids"
    ],
    "models": {
      "Maleceptor": [1, 1]
    },
    "equipment": [
      "Psychic Overload",
      "Massive scything talons - strike",
      "Massive scything talons - sweep"
    ]
  },

  {
    "name": "Pyrovores",
    "points": [30, 60, 90],
    "stats": {
      "movement": 5,
      "toughness": 6,
      "save": 3,
      "invulnerable": 7,
      "wounds": 4,
      "leadership": 8,
      "objective_control": 1
    },
    "weapons": [
      {
        "name": "Flamespurt",
        "range": 12,
        "attacks": 1,
        "attack_dice": "d6",
        "hit": 0,
        "strength": 6,
        "armour_pen": 1,
        "damage": 1,
        "tags": ["Ignores Cover", "Torrent", "Twin-Linked"],
        "ranged": true
      },
      {
        "name": "Chitin-barbed limbs",
        "range": 0,
        "attacks": 2,
        "hit": 4,
        "strength": 5,
        "armour_pen": 0,
        "damage": 1,
        "tags": [],
        "ranged": false
      }
    ],
    "abilities": {
      "Core": ["Deadly Demise 1"],
      "synapse": false,
      "Burning Spray": "In your Shooting phase, after this unit has shot, select one enemy unit hit by one or more of those attacks. Until the end of the phase, that enemy unit cannot have the Benefit of Cover."
    },
    "tags": ["Infantry", "Great Devourer", "Pyrovores", "Tyranids"],
    "models": {
      "Pyrovores": [1, 2, 3]
    },
    "equipment": ["Flamespurt", "Chitin-barbed limbs"]
  },

  {
    "name": "Haruspex",
    "points": [125],
    "stats": {
      "movement": 8,
      "toughness": 11,
      "save": 3,
      "invulnerable": 7,
      "wounds": 14,
      "leadership": 8,
      "objective_control": 4
    },
    "weapons": [
      {
        "name": "Grasping Tongue",
        "range": 12,
        "attacks": 1,
        "hit": 3,
        "strength": 6,
        "armour_pen": 2,
        "damage": 1,
        "damage_dice": "d6",
        "tags": ["Precision"],
        "ranged": true
      },
      {
        "name": "Ravenous Maw",
        "range": 0,
        "attacks": 14,
        "hit": 3,
        "strength": 7,
        "armour_pen": 1,
        "damage": 2,
        "tags": [],
        "ranged": false
      },
      {
        "name": "Shovelling Claws",
        "range": 0,
        "attacks": 4,
        "hit": 3,
        "strength": 14,
        "armour_pen": 2,
        "damage": 1,
        "damage_dice": "d6",
        "tags": ["Extra Attacks"],
        "ranged": false
      }
    ],
    "abilities": {
      "Core": ["Deadly Demise D3"],
      "synapse": false,
      "Grisly Spectecle": "Each time this model is selected to fight, after resolving its attacks, if one or more enemy units were destroyed by those attacks, each enemy unit within 6 inches of this model must take a Battle-shock test.",
      "Damaged": "While this model has 1-5 wounds remaining, each time this model makes an attack, subtract 1 from the Hit roll."
    },
    "tags": ["Monster", "Great Devourer", "Haruspex", "Tyranids"],
    "models": {
      "Haruspex": [1, 1]
    },
    "equipment": ["Grasping Tongue", "Ravenous Maw", "Shovelling Claws"]
  },

  {
    "name": "Venomthropes",
    "points": [70, 140],
    "stats": {
      "movement": 6,
      "toughness": 5,
      "save": 4,
      "invulnerable": 7,
      "wounds": 3,
      "leadership": 8,
      "objective_control": 1
    },
    "weapons": [
      {
        "name": "Toxic Lashes",
        "range": 0,
        "attacks": 5,
        "hit": 3,
        "strength": 3,
        "armour_pen": 0,
        "damage": 1,
        "tags": ["Anti-Infantry 2+"],
        "ranged": false
      }
    ],
    "abilities": {
      "Core": ["Stealth"],
      "synapse": false,
      "Foul Spore [Aura]": "While a friendly Tyranids unit is within 6 inches of this unit, each time a ranged attack targets that unit, models in that unit have the Benefit of Cover against that attack. In addition, while a friendly Tyranids unit (excluding Monsters) is within 6 inches of this unit, models in that unit have the Stealth ability."
    },
    "tags": ["Infantry", "fly", "Great Devourer", "Venomthropes", "Tyranids"],
    "models": {
      "Venomthropes": [3, 6]
    },
    "equipment": ["Toxic Lashes"]
  },

  {
    "name": "Von Ryan's Leapers",
    "points": [75, 150],
    "stats": {
      "movement": 10,
      "toughness": 5,
      "save": 4,
      "invulnerable": 6,
      "wounds": 3,
      "leadership": 8,
      "objective_control": 1
    },
    "weapons": [
      {
        "name": "Leapers Talons",
        "range": 0,
        "attacks": 6,
        "hit": 3,
        "strength": 5,
        "armour_pen": 1,
        "damage": 1,
        "tags": [],
        "ranged": false
      }
    ],
    "abilities": {
      "Core": ["Fights First", "Infiltrators", "Stealth"],
      "synapse": false,
      "Pouncing Leap": "You can target this unit with the Heroic Intervention Stratagem for 0CP, and can do so even if you have already used that Stratagem on a different unit this phase."
    },
    "tags": ["Infantry", "Great Devourer", "Von Ryan's Leapers", "Tyranids"],
    "models": {
      "Von Ryan's Leapers": [3, 6]
    },
    "equipment": ["Leapers Talons"]
  },

  {
    "name": "Neurogaunts",
    "points": [45, 90],
    "stats": {
      "movement": 6,
      "toughness": 3,
      "save": 6,
      "invulnerable": 7,
      "wounds": 1,
      "leadership": 8,
      "objective_control": 1
    },
    "weapons": [
      {
        "name": "Xenos claws and teeth",
        "range": 0,
        "attacks": 1,
        "hit": 4,
        "strength": 3,
        "armour_pen": 0,
        "damage": 1,
        "tags": [],
        "ranged": true
      }
    ],
    "abilities": {
      "synapse": false,
      "Neurocytes": "While this unit is within Synapse Range of your army, it has the Synapse keyword."
    },
    "tags": [
      "Infantry",
      "Great Devourer",
      "Endless Multitude",
      "Neurogaunts",
      "Tyranids"
    ],
    "models": {
      "NeuroGaunt Nodebeasts": [1, 2],
      "Neurogaunts": [10, 20]
    },
    "equipment": ["Xenos claws and teeth"]
  },

  {
    "name": "Zoanthropes",
    "points": [90, 180],
    "stats": {
      "movement": 5,
      "toughness": 5,
      "save": 5,
      "invulnerable": 4,
      "wounds": 3,
      "leadership": 7,
      "objective_control": 1
    },
    "weapons": [
      {
        "name": "Warp Blast - Witchfire",
        "range": 24,
        "attacks": 0,
        "attack_dice": "d3",
        "hit": 3,
        "strength": 7,
        "armour_pen": 2,
        "damage": 0,
        "damage_dice": "d3",
        "tags": ["Blast", "Psychic"],
        "ranged": true
      },
      {
        "name": "Warp Blast - Focused Witchfire",
        "range": 24,
        "attacks": 1,
        "hit": 3,
        "strength": 12,
        "armour_pen": 3,
        "damage": 1,
        "damage_dice": "d6",
        "tags": ["Lethal Hits", "Psychic"],
        "ranged": true
      },
      {
        "name": "Xenos claws and teeth",
        "range": 0,
        "attacks": 2,
        "hit": 5,
        "strength": 3,
        "armour_pen": 0,
        "damage": 1,
        "tags": [],
        "ranged": false
      }
    ],
    "abilities": {
      "Shadow in the Warp": "If your Army Faction is Tyranids, once per battle, in either player’s Command phase, if one or more units from your army with this ability are on the battlefield, you can unleash the Shadow in the Warp. When you do, each enemy unit on the battlefield must take a Battle-shock test.",
      "synapse": true,
      "Spirit Leech [Aura, psychic]": "While this unit contains a Neurothrope, while an enemy unit is within 6 inches of this unit, each time that enemy unit fails a Battle-shock test, it suffers D3 mortal wounds and one model in this unit regains up to D3 lost wounds.",
      "Warp Field [Aura, psychic": "While a friendly Tyranids unit is within 6 inches of this unit, models in that unit have a 6+ invulnerable save."
    },
    "tags": [
      "Infantry",
      "Psyker",
      "fly",
      "Great Devourer",
      "Synapse",
      "Zoanthropes",
      "Tyranids"
    ],
    "models": {
      "Neurothrope": [1, 1],
      "Zoanthropes": [2, 5]
    },
    "equipment": [
      "Warp Blast - Witchfire",
      "Warp Blast - Focused Witchfire",
      "Xenos claws and teeth"
    ]
  },

  {
    "name": "Genestealers",
    "points": [90, 180],
    "stats": {
      "movement": 8,
      "toughness": 4,
      "save": 5,
      "invulnerable": 5,
      "wounds": 2,
      "leadership": 7,
      "objective_control": 1
    },
    "weapons": [
      {
        "name": "Genestealer Claws and Talons",
        "range": 0,
        "attacks": 4,
        "hit": 2,
        "strength": 4,
        "armour_pen": 2,
        "damage": 1,
        "tags": [],
        "ranged": false
      }
    ],
    "abilities": {
      "Core": ["Scouts 8 inches"],
      "Vanguard Predator": "Each time a model in this unit makes an attack, re-roll a Wound roll of 1. If the target is within range of an objective marker, you can re-roll the Wound roll instead.",
      "synapse": false
    },
    "tags": ["Infantry", "Genestealers", "Great Devourer"],
    "models": {
      "Genestealers": [5, 10]
    },
    "equipment": ["Genestealer Claws and Talons"]
  },

  {
    "name": "Raveners",
    "points": [75, 150],
    "stats": {
      "movement": 10,
      "toughness": 5,
      "save": 4,
      "invulnerable": 7,
      "wounds": 3,
      "leadership": 8,
      "objective_control": 1
    },
    "weapons": [
      {
        "name": "Thoracic Bio-Weapon",
        "range": 12,
        "attacks": 3,
        "hit": 4,
        "strength": 4,
        "armour_pen": 0,
        "damage": 1,
        "tags": [],
        "ranged": true
      },
      {
        "name": "Ravener Claws and Talons",
        "range": 0,
        "attacks": 7,
        "hit": 3,
        "strength": 5,
        "armour_pen": 1,
        "damage": 1,
        "tags": ["Twin-Linked"],
        "ranged": false
      }
    ],
    "abilities": {
      "Core": ["Deep Strike"],
      "synapse": false,
      "Death from below": "At the end of your opponent’s turn, if this unit is not within Engagement Range of one or more enemy units, you can remove it from the battlefield and place it into Strategic Reserves."
    },
    "tags": ["Infantry", "Great Devourer", "Raveners", "Tyranids"],
    "models": {
      "Raveners": [3, 6]
    },
    "equipment": ["Ravener Claws and Talons"]
  },

  {
    "name": "Ripper Swarms",
    "points": [35, 70],
    "stats": {
      "movement": 6,
      "toughness": 2,
      "save": 6,
      "invulnerable": 7,
      "wounds": 4,
      "leadership": 8,
      "objective_control": 0
    },
    "weapons": [
      {
        "name": "Spinemaws",
        "range": 6,
        "attacks": 4,
        "hit": 5,
        "strength": 3,
        "armour_pen": 0,
        "damage": 1,
        "tags": ["Pistol"],
        "ranged": true
      },
      {
        "name": "Xenos claws and teeth",
        "range": 0,
        "attacks": 6,
        "hit": 5,
        "strength": 2,
        "armour_pen": 0,
        "damage": 1,
        "tags": ["Sustained Hits 1"],
        "ranged": false
      }
    ],
    "abilities": {
      "Core": ["Deep Strike"],
      "synapse": false,
      "Chitinous Horrors [Aura]": "While an enemy unit is within Engagement Range of this unit, halve the Objective Control characteristic of models in that enemy unit."
    },
    "tags": ["Swarm", "Great Devourer", "Ripper Swarms", "Tyranids"],
    "models": {
      "Ripper Swarms": [3, 6]
    },
    "equipment": ["Xenos claws and teeth"]
  },

  {
    "name": "Parasite of Mortrex",
    "points": [90],
    "stats": {
      "movement": 12,
      "toughness": 5,
      "save": 4,
      "invulnerable": 7,
      "wounds": 5,
      "leadership": 8,
      "objective_control": 1
    },
    "weapons": [
      {
        "name": "Barbed Ovipositor",
        "range": 0,
        "attacks": 1,
        "hit": 2,
        "strength": 3,
        "armour_pen": 2,
        "damage": 3,
        "tags": ["Anti-Infantry 3+", "Extra Attacks"],
        "ranged": false
      },
      {
        "name": "Clawed Limbs",
        "range": 0,
        "attacks": 6,
        "hit": 2,
        "strength": 5,
        "armour_pen": 1,
        "damage": 1,
        "tags": [],
        "ranged": false
      }
    ],
    "abilities": {
      "Core": ["Deep Strike", "Lone Operative", "Stealth"],
      "synapse": false,
      "Parasitic Infection": "Each time an Infantry model is destroyed by an attack made with this model’s barbed ovipositor, after this model has finished making its attacks, you can add one new Ripper Swarms unit to your army consisting of D3 models and set it up within 3 inches of this model. If you do, that Ripper Swarms unit can be set up within Engagement Range of the destroyed model’s unit (but not within Engagement Range of any other enemy units).",
      "It Itches!": "At the start of the Fight phase, select one enemy unit within Engagement Range of this model. That enemy unit must take a Battle-shock test."
    },
    "tags": [
      "Infantry",
      "Character",
      "fly",
      "Great Devourer",
      "Parasite of Mortrex",
      "Tyranids"
    ],
    "models": {
      "Parasite of Mortrex": [1, 1]
    },
    "equipment": ["Barbed Ovipositor", "Clawed Limbs"]
  },

  {
    "name": "Mawloc",
    "points": [145],
    "stats": {
      "movement": 10,
      "toughness": 10,
      "save": 3,
      "invulnerable": 7,
      "wounds": 14,
      "leadership": 8,
      "objective_control": 4
    },
    "weapons": [
      {
        "name": "Distensible Jaw",
        "range": 0,
        "attacks": 1,
        "hit": 3,
        "strength": 5,
        "armour_pen": 0,
        "damage": 3,
        "tags": ["Anti-Infantry 4+", "Devastating Wounds", "Extra Attacks"],
        "ranged": true
      },
      {
        "name": "Mawlock Scything Talons",
        "range": 0,
        "attacks": 16,
        "hit": 3,
        "strength": 8,
        "armour_pen": 2,
        "damage": 1,
        "tags": [],
        "ranged": false
      }
    ],
    "abilities": {
      "Core": ["Deep Strike"],
      "synapse": false,
      "Terror from the Deep": "Each time this unit is set up on the battlefield using the Deep Strike ability, roll one D6 for each enemy unit within 12 inches of this model: on a 2-4, that unit suffers D3 mortal wounds; on a 5+, that unit suffers 3 mortal wounds and must take a Battle-shock test.",
      "Damaged": "While this model has 1-5 wounds remaining, each time this model makes an attack, subtract 1 from the Hit roll."
    },
    "tags": ["Monster", "Great Devourer", "Mawloc", "Tyranids"],
    "models": {
      "Mawloc": [1, 1]
    },
    "equipment": ["Distensible Jaw", "Mawlock Scything Talons"]
  },

  {
    "name": "Trygon",
    "points": [180],
    "stats": {
      "movement": 10,
      "toughness": 10,
      "save": 3,
      "invulnerable": 7,
      "wounds": 14,
      "leadership": 8,
      "objective_control": 4
    },
    "weapons": [
      {
        "name": "Bio-electric Pulse",
        "range": 12,
        "attacks": 6,
        "hit": 3,
        "strength": 5,
        "armour_pen": 0,
        "damage": 1,
        "tags": ["Sustained Hits 2"],
        "ranged": true
      },
      {
        "name": "Trygon Scything Talons",
        "range": 0,
        "attacks": 12,
        "hit": 3,
        "strength": 9,
        "armour_pen": 2,
        "damage": 3,
        "tags": [],
        "ranged": false
      }
    ],
    "abilities": {
      "Core": ["Deep Strike"],
      "synapse": false,
      "Subterranean Tunnels": "Each time this model is set up on the battlefield using the Deep Strike ability, it can be set up anywhere on the battlefield that is more than 3 inches horizontally away from all enemy units. When doing so, if this model is set up within 9 inches of one or more enemy units, until the end of the turn, it is not eligible to declare a charge.",
      "Damaged": "While this model has 1-5 wounds remaining, each time this model makes an attack, subtract 1 from the Hit roll."
    },
    "tags": ["Monster", "Great Devourer", "Trygon", "Tyranids"],
    "models": {
      "Trygon": [1, 1]
    },
    "equipment": ["Bio-electric Pulse", "Trygon Scything Talons"]
  },

  {
    "name": "Mucolid Spores",
    "points": [45, 90],
    "stats": {
      "movement": 4,
      "toughness": 4,
      "save": 7,
      "invulnerable": 7,
      "wounds": 3,
      "leadership": 8,
      "objective_control": 0
    },
    "abilities": {
      "Core": ["Deep Strike"],
      "synapse": false,
      "Bio-minefield": "Enemy units cannot start or end an Advance move within 6 inches of this unit.",
      "Floating Death": "Each time an enemy unit ends a move within 3 inches of a model in this unit, and each time a model in this unit ends a move within 3 inches of an enemy unit, roll one D6: on a 2-5, that enemy unit suffers D3 mortal wounds; on a 6, that enemy unit suffers D6 mortal wounds. The model in this unit that caused that roll is then destroyed."
    },
    "tags": ["Beast", "fly", "Great Devourer", "Mucolid Spores", "Tyranids"],
    "models": {
      "Mucolid Spores": [1, 2]
    }
  },

  {
    "name": "Spore Mines",
    "points": [50, 100],
    "stats": {
      "movement": 4,
      "toughness": 1,
      "save": 7,
      "invulnerable": 7,
      "wounds": 1,
      "leadership": 8,
      "objective_control": 0
    },
    "abilities": {
      "Core": ["Deep Strike"],
      "synapse": false,
      "Bio-minefield": "Enemy units cannot start or end an Advance move within 6 inches of this unit.",
      "Floating Death": "Each time an enemy unit ends a move within 3 inches of a model in this unit, and each time a model in this unit ends a move within 3 inches of an enemy unit, roll one D6: on a 2-5, that enemy unit suffers 1 mortal wound; on a 6, that enemy unit suffers D3 mortal wounds. The model in this unit that caused that roll is then destroyed."
    },
    "tags": ["Beast", "fly", "Great Devourer", "Spore Mines", "Tyranids"],
    "models": {
      "Mucolid Spores": [1, 2]
    }
  },

  {
    "name": "Exocrine",
    "points": [135],
    "stats": {
      "movement": 8,
      "toughness": 10,
      "save": 3,
      "invulnerable": 7,
      "wounds": 14,
      "leadership": 8,
      "objective_control": 4
    },
    "weapons": [
      {
        "name": "Bio-plasmic Cannon",
        "range": 36,
        "attacks": 3,
        "attacks_dice": "1d6",
        "hit": 3,
        "strength": 8,
        "armour_pen": 3,
        "damage": 3,
        "tags": ["Blast", "Heavy"],
        "ranged": true
      },
      {
        "name": "Powerful Limbs",
        "range": 0,
        "attacks": 3,
        "hit": 3,
        "strength": 7,
        "armour_pen": 0,
        "damage": 2,
        "tags": [],
        "ranged": false
      }
    ],
    "abilities": {
      "Core": ["Deadly Demise D3"],
      "synapse": false,
      "Symbiotic Targeting": "In your Shooting phase, after this model has shot, select one enemy unit hit by one or more of those attacks. Until the end of the phase, each time a friendly Tyranids model makes an attack that targets that unit, re-roll a Hit roll of 1.",
      "Damaged": "While this model has 1-5 wounds remaining, each time this model makes an attack, subtract 1 from the Hit roll."
    },
    "tags": ["Monster", "Great Devourer", "Exocrine", "Tyranids"],
    "models": {
      "Exocrine": [1, 1]
    },
    "equipment": ["Bio-plasmic Cannon", "Powerful Limbs"]
  },

  {
    "name": "Biovores",
    "points": [40, 80, 120],
    "stats": {
      "movement": 5,
      "toughness": 6,
      "save": 4,
      "invulnerable": 7,
      "wounds": 4,
      "leadership": 8,
      "objective_control": 1
    },
    "weapons": [
      {
        "name": "Spore Mine Launcher",
        "range": 48,
        "attacks": 0,
        "attack_dice": "d3",
        "hit": 4,
        "strength": 6,
        "armour_pen": 1,
        "damage": 2,
        "tags": ["Blast", "Devastating Wounds", "Heavy", "Indirect Fire"],
        "ranged": true
      },
      {
        "name": "Chitin-barbed Limbs",
        "range": 0,
        "attacks": 2,
        "hit": 4,
        "strength": 5,
        "armour_pen": 0,
        "damage": 1,
        "tags": [],
        "ranged": false
      }
    ],
    "abilities": {
      "Core": ["Deadly Demise 1"],
      "synapse": false,
      "Seed Spore Mines": "In your Shooting phase, each time this unit is selected to shoot, it can use this ability instead of making any attacks with its ranged weapons. If it does, you can add a new Spore Mines unit to your army and set it up anywhere on the battlefield that is within 48 inches of this unit but more than 9 inches horizontally away from all enemy units. That Spore Mines unit contains 1 model for each model in this unit."
    },
    "tags": ["Infantry", "Great Devourer", "Biovores", "Tyranids"],
    "models": {
      "Biovores": [1, 2, 3]
    },
    "equipment": ["Spore Mine Launcher", "Chitin-barbed Limbs"]
  },

  {
    "name": "Carnifexes",
    "points": [125, 250],
    "stats": {
      "movement": 8,
      "toughness": 9,
      "save": 2,
      "invulnerable": 7,
      "wounds": 8,
      "leadership": 8,
      "objective_control": 3
    },
    "weapons": [
      {
        "name": "Bio-Plasma",
        "range": 12,
        "attacks": 0,
        "attack_dice": "d3",
        "hit": 4,
        "strength": 7,
        "armour_pen": 2,
        "damage": 1,
        "tags": ["Assault", "Blast"],
        "ranged": true
      },
      {
        "name": "Deathspitters with Slimer Maggots",
        "range": 24,
        "attacks": 6,
        "hit": 4,
        "strength": 7,
        "armour_pen": 2,
        "damage": 1,
        "tags": [],
        "ranged": true
      },
      {
        "name": "Devourers with Brainleech Worms",
        "range": 18,
        "attacks": 12,
        "hit": 4,
        "strength": 6,
        "armour_pen": 0,
        "damage": 1,
        "tags": [],
        "ranged": true
      },
      {
        "name": "Heavy Venom Cannon",
        "range": 36,
        "attacks": 0,
        "attack_dice": "d3",
        "hit": 4,
        "strength": 9,
        "armour_pen": 2,
        "damage": 3,
        "tags": ["Blast"],
        "ranged": true
      },
      {
        "name": "Spine Banks",
        "range": 6,
        "attacks": 5,
        "hit": 4,
        "strength": 5,
        "armour_pen": 0,
        "damage": 1,
        "tags": ["Assault"],
        "ranged": true
      },
      {
        "name": "Stranglethorn Cannon",
        "range": 36,
        "attacks": 1,
        "attack_dice": "d6",
        "hit": 4,
        "strength": 7,
        "armour_pen": 1,
        "damage": 2,
        "tags": ["Blast"],
        "ranged": true
      },
      {
        "name": "Carnifex Crushing Claws",
        "range": 0,
        "attacks": 4,
        "hit": 4,
        "strength": 12,
        "armour_pen": 3,
        "damage": 1,
        "damage_dice": "d6",
        "tags": [],
        "ranged": false
      },
      {
        "name": "Carnifex Extra Scything Talons",
        "range": 0,
        "attacks": 2,
        "hit": 4,
        "strength": 9,
        "armour_pen": 2,
        "damage": 3,
        "tags": ["Extra Attacks"],
        "ranged": false
      },
      {
        "name": "Carnifex Scything Talons",
        "range": 0,
        "attacks": 6,
        "hit": 4,
        "strength": 9,
        "armour_pen": 2,
        "damage": 3,
        "tags": [],
        "ranged": false
      },
      {
        "name": "Xenos claws and teeth",
        "range": 0,
        "attacks": 4,
        "hit": 4,
        "strength": 6,
        "armour_pen": 0,
        "damage": 1,
        "tags": [],
        "ranged": false
      }
    ],
    "abilities": {
      "Core": ["Deadly Demise 1"],
      "synapse": false,
      "Blistering Assault": "Each time an enemy unit is selected to shoot, after that unit has shot, if any models from this unit lost one or more wounds as a result of those attacks, this unit can make a Blistering Assault move. To do so, roll one D6, adding 2 to the result: each model in this unit can be moved a distance in inches up to the result, but this unit must finish that move as close as possible to the closest enemy unit. When doing so, those models can be moved within Engagement Range of that enemy unit. Each unit can only make one Blistering Assault move per phase."
    },
    "tags": ["Monster", "Great Devourer", "Carnifexes", "Tyranids"],
    "models": {
      "Carnifexes": [1, 2]
    },
    "equipment": [
      "Carnifex Scything Talons",
      "Carnifex Extra Scything Talons",
      "Xenos claws and teeth"
    ]
  },

  {
    "name": "Screamer-Killer",
    "points": [180],
    "stats": {
      "movement": 8,
      "toughness": 9,
      "save": 2,
      "invulnerable": 7,
      "wounds": 10,
      "leadership": 8,
      "objective_control": 3
    },
    "weapons": [
      {
        "name": "Bio-Plasmic Scream",
        "range": 18,
        "attacks": 3,
        "attacks_dice": "1d6",
        "hit": 4,
        "strength": 8,
        "armour_pen": 2,
        "damage": 1,
        "tags": ["Assault", "Blast"],
        "ranged": true
      },
      {
        "name": "Screamer-Killer Talons",
        "range": 0,
        "attacks": 10,
        "hit": 3,
        "strength": 10,
        "armour_pen": 2,
        "damage": 3,
        "tags": [],
        "ranged": false
      }
    ],
    "abilities": {
      "Core": ["Deadly Demise 1"],
      "synapse": false,
      "Death Scream": "In your Shooting phase, after this model has shot, select one unit hit by one or more of those attacks. That unit must take a Battle-shock test, subtracting 1 from that test."
    },
    "tags": ["Monster", "Great Devourer", "Screamer-Killer", "Tyranids"],
    "models": {
      "Screamer-Killer": [1, 1]
    },
    "equipment": ["Bio-Plasmic Scream", "Screamer-Killer Talons"]
  },

  {
    "name": "Hive Guard",
    "points": [100, 200],
    "stats": {
      "movement": 6,
      "toughness": 7,
      "save": 3,
      "invulnerable": 7,
      "wounds": 4,
      "leadership": 8,
      "objective_control": 1
    },
    "weapons": [
      {
        "name": "Impaler Cannon",
        "range": 36,
        "attacks": 4,
        "hit": 4,
        "strength": 5,
        "armour_pen": 1,
        "damage": 1,
        "tags": ["Heavy", "Indirect Fire"],
        "ranged": true
      },
      {
        "name": "Shockcannon",
        "range": 24,
        "attacks": 2,
        "hit": 3,
        "strength": 7,
        "armour_pen": 1,
        "damage": 3,
        "tags": ["Anti-vechicle 2+"],
        "ranged": true
      },
      {
        "name": "Xenos claws and teeth",
        "range": 0,
        "attacks": 3,
        "hit": 4,
        "strength": 5,
        "armour_pen": 0,
        "damage": 1,
        "tags": [],
        "ranged": false
      }
    ],
    "abilities": {
      "synapse": false,
      "Defensive Stance": "Each time you target this unit with the Fire Overwatch Stratagem, while resolving that Stratagem, hits are scored on unmodified Hit rolls of 5+, or unmodified Hit rolls of 4+ instead if this unit is within range of an objective marker."
    },
    "tags": ["Infantry", "Great Devourer", "Hive Guard", "Tyranids"],
    "models": {
      "Hive Guard": [3, 6]
    },
    "equipment": ["Shockcannon", "Xenos claws and teeth"]
  },

  {
    "name": "Tyrannofex",
    "points": [200],
    "stats": {
      "movement": 9,
      "toughness": 12,
      "save": 2,
      "invulnerable": 7,
      "wounds": 16,
      "leadership": 8,
      "objective_control": 5
    },
    "weapons": [
      {
        "name": "Acid Spray",
        "range": 18,
        "attacks": 6,
        "attacks_dice": "1d6",
        "hit": 0,
        "strength": 6,
        "armour_pen": 2,
        "damage": 2,
        "tags": ["Torrent"],
        "ranged": true
      },
      {
        "name": "Fleshborer Hive",
        "range": 24,
        "attacks": 20,
        "hit": 3,
        "strength": 5,
        "armour_pen": 0,
        "damage": 1,
        "tags": ["Heavy", "Sustained Hits 1", "Twin-Linked"],
        "ranged": true
      },
      {
        "name": "Rupture Cannon",
        "range": 48,
        "attacks": 2,
        "hit": 3,
        "strength": 18,
        "armour_pen": 4,
        "damage": 0,
        "damage_dice": "2d6",
        "tags": ["Heavy"],
        "ranged": true
      },
      {
        "name": "Stinger salvoes",
        "range": 24,
        "attacks": 8,
        "hit": 3,
        "strength": 5,
        "armour_pen": 0,
        "damage": 1,
        "tags": [],
        "ranged": true
      },
      {
        "name": "Powerful Limbs",
        "range": 0,
        "attacks": 4,
        "hit": 3,
        "strength": 8,
        "armour_pen": 0,
        "damage": 2,
        "tags": [],
        "ranged": false
      }
    ],
    "abilities": {
      "synapse": false,
      "Resilient Organism": "Each time an attack is allocated to this model, subtract 1 from the Damage characteristic of that attack.",
      "Damaged": "While this model has 1-5 wounds remaining, each time this model makes an attack, subtract 1 from the Hit roll."
    },
    "tags": ["Monster", "Great Devourer", "Tyrannofex", "Tyranids"],
    "models": {
      "Tyrannofex": [1, 1]
    },
    "equipment": ["Fleshborer Hive", "Stinger salvoes", "Powerful Limbs"]
  },

  {
    "name": "Tyrannocyte",
    "points": [105],
    "stats": {
      "movement": 8,
      "toughness": 9,
      "save": 3,
      "invulnerable": 7,
      "wounds": 10,
      "leadership": 8,
      "objective_control": 2
    },
    "weapons": [
      {
        "name": "Tyrannocyte Bio-Weapons",
        "range": 24,
        "attacks": 5,
        "hit": 4,
        "strength": 5,
        "armour_pen": 1,
        "damage": 2,
        "tags": [],
        "ranged": true
      },
      {
        "name": "Flensing Whips",
        "range": 0,
        "attacks": 6,
        "hit": 4,
        "strength": 7,
        "armour_pen": 1,
        "damage": 2,
        "tags": [],
        "ranged": false
      }
    ],
    "abilities": {
      "Core": ["Deadly Demise D3", "Deep Strike"],
      "synapse": false,
      "Aerial Seeding": "This model must start the battle in Reserves, but neither it nor any units embarked within it are counted towards any limits placed on the maximum number of Reserves units you can start the battle with. This model can be set up in the Reinforcements step of your first, second or third Movement phase, regardless of any mission rules. Any units embarked within this model must immediately disembark after it has been set up on the battlefield, and they must be set up more than 9 inches away from all enemy models. After this model has been set up on the battlefield, no units can embark within it."
    },
    "tags": [
      "Monster",
      "fly",
      "Transport",
      "Dedicated Transport",
      "Great Devourer",
      "Tyrannocyte",
      "Tyranids"
    ],
    "models": {
      "Tyrannocyte": [1, 1]
    },
    "equipment": ["Tyrannocyte Bio-Weapons", "Flensing Whips"]
  },

  {
    "name": "Hive Crone",
    "points": [200],
    "stats": {
      "movement": 20,
      "toughness": 9,
      "save": 3,
      "invulnerable": 7,
      "wounds": 12,
      "leadership": 8,
      "objective_control": 0
    },
    "weapons": [
      {
        "name": "Drool Cannon",
        "range": 12,
        "attacks": 0,
        "attacks_dice": "2d6",
        "hit": 0,
        "strength": 6,
        "armour_pen": 1,
        "damage": 1,
        "tags": ["Torrent"],
        "ranged": true
      },
      {
        "name": "Stinger salvoes",
        "range": 24,
        "attacks": 8,
        "hit": 3,
        "strength": 5,
        "armour_pen": 0,
        "damage": 1,
        "tags": [],
        "ranged": true
      },
      {
        "name": "Tentaclids",
        "range": 36,
        "attacks": 4,
        "hit": 3,
        "strength": 7,
        "armour_pen": 0,
        "damage": 2,
        "tags": ["Anti-vechicle 4+", "Devastating Wounds"],
        "ranged": true
      },
      {
        "name": "Scything Wings",
        "range": 0,
        "attacks": 4,
        "hit": 4,
        "strength": 7,
        "armour_pen": 1,
        "damage": 2,
        "tags": [],
        "ranged": false
      },
      {
        "name": "Thorax Spur",
        "range": 0,
        "attacks": 1,
        "hit": 3,
        "strength": 10,
        "armour_pen": 3,
        "damage": 0,
        "damage_dice": "d6",
        "tags": ["Anti-fly 2+", "Extra Attacks"],
        "ranged": false
      }
    ],
    "abilities": {
      "Core": ["Deadly Demise D3", "Hover"],
      "synapse": false,
      "Airborne Predator": "Each time this model makes a ranged attack that targets a unit that can Fly, add 1 to the Hit roll.",
      "Damaged": "While this model has 1-4 wounds remaining, each time this model makes an attack, subtract 1 from the Hit roll."
    },
    "tags": [
      "Monster",
      "fly",
      "Aircraft",
      "Great Devourer",
      "Hive Crone",
      "Tyranids"
    ],
    "models": {
      "Hive Crone": [1, 1]
    },
    "equipment": [
      "Drool Cannon",
      "Stinger salvoes",
      "Scything Wings",
      "Thorax Spur"
    ]
  },

  {
    "name": "Harpy",
    "points": [170],
    "stats": {
      "movement": 20,
      "toughness": 9,
      "save": 3,
      "invulnerable": 7,
      "wounds": 12,
      "leadership": 8,
      "objective_control": 0
    },
    "weapons": [
      {
        "name": "Stinger salvoes",
        "range": 24,
        "attacks": 8,
        "hit": 3,
        "strength": 5,
        "armour_pen": 0,
        "damage": 1,
        "tags": [],
        "ranged": true
      },
      {
        "name": "Twin Heavy Venom Cannon",
        "range": 36,
        "attacks": 0,
        "attack_dice": "d3",
        "hit": 3,
        "strength": 9,
        "armour_pen": 2,
        "damage": 3,
        "tags": ["Blast", "Twin-Linked"],
        "ranged": true
      },
      {
        "name": "Twin Heavy Stranglethorn Cannon",
        "range": 36,
        "attacks": 1,
        "attack_dice": "d6",
        "hit": 2,
        "strength": 7,
        "armour_pen": 1,
        "damage": 2,
        "tags": ["Blast", "Twin-Linked"],
        "ranged": true
      },
      {
        "name": "Scything Wings",
        "range": 0,
        "attacks": 4,
        "hit": 4,
        "strength": 7,
        "armour_pen": 1,
        "damage": 2,
        "tags": [],
        "ranged": false
      }
    ],
    "abilities": {
      "Core": ["Deadly Demise D3", "Hover"],
      "synapse": false,
      "Spore Mine Cysts": "Each time this model ends a Normal move, you can do one of the following: ■ Select one enemy unit it moved over during that move and roll six D6: for each 3+, that unit suffers 1 mortal wound. ■ Add a new Spore Mines unit containing D3 models to your army and set it up anywhere on the battlefield that is within 6 inches of this model and more than 9 inches horizontally away from all enemy units.",
      "Damaged": "While this model has 1-4 wounds remaining, each time this model makes an attack, subtract 1 from the Hit roll."
    },
    "tags": [
      "Monster",
      "fly",
      "Aircraft",
      "Great Devourer",
      "Harpy",
      "Tyranids"
    ],
    "models": {
      "Harpy": [1, 1]
    },
    "equipment": [
      "Stinger salvoes",
      "Twin Heavy Stranglethorn Cannon",
      "Scything Wings"
    ]
  },

  {
    "name": "Sporocyst",
    "points": [145],
    "stats": {
      "movement": 0,
      "toughness": 10,
      "save": 3,
      "invulnerable": 7,
      "wounds": 10,
      "leadership": 8,
      "objective_control": 0
    },
    "weapons": [
      {
        "name": "Sporocyst Bio-Weapons",
        "range": 24,
        "attacks": 5,
        "hit": 4,
        "strength": 5,
        "armour_pen": 1,
        "damage": 2,
        "tags": ["Hive Defences"],
        "ranged": true
      },
      {
        "name": "Flensing Whips",
        "range": 0,
        "attacks": 6,
        "hit": 4,
        "strength": 7,
        "armour_pen": 1,
        "damage": 1,
        "tags": [],
        "ranged": false
      }
    ],
    "abilities": {
      "Core": ["Deadly Demise D3"],
      "synapse": false,
      "Seed Mucolids": "In your Shooting phase, each time this model is selected to shoot, it can use this ability instead of making any attacks with its ranged weapons. If it does, you can add a new Mucolid Spores unit containing 1 model to your army and set it up anywhere on the battlefield that is within 18 inches of this model but more than 9 inches horizontally away from all enemy units.",
      "Hive Defences": "Each time an enemy unit is set up or ends a Normal, Advance or Fall Back move within range of this weapon, if that enemy unit is an eligible target, the bearer can shoot with this weapon at that unit as if it were your Shooting phase (the bearer can do so up to four times per phase)."
    },
    "tags": ["Monster", "Great Devourer", "Sporocyst", "Tyranids"],
    "models": {
      "Sporocyst": [1, 1]
    },
    "equipment": ["Sporocyst Bio-Weapons", "Flensing Whips"]
  },

  {
    "name": "Psychophage",
    "points": [125],
    "stats": {
      "movement": 8,
      "toughness": 9,
      "save": 3,
      "invulnerable": 7,
      "wounds": 10,
      "leadership": 8,
      "objective_control": 3
    },
    "weapons": [
      {
        "name": "Psychoclastic Torrent",
        "range": 12,
        "attacks": 0,
        "attack_dice": "d6",
        "hit": 0,
        "strength": 6,
        "armour_pen": 1,
        "damage": 1,
        "tags": ["Ignores Cover", "Torrent"],
        "ranged": true
      },
      {
        "name": "Talons and Betentacled Maw",
        "range": 0,
        "attacks": 1,
        "attack_dice": "d6",
        "hit": 3,
        "strength": 6,
        "armour_pen": 1,
        "damage": 2,
        "tags": ["Anti-Psyker 2+", "Devastating Wounds"],
        "ranged": false
      }
    ],
    "abilities": {
      "Core": ["Deadly Demise 1", "Feel No Pain 5+"],
      "synapse": false,
      "Bio-Stimulus [Aura]": "While a friendly Tyranids unit is within 6 inches of this model, models in that unit have the Feel No Pain 6+ ability.",
      "Feeding Frenzy": "Each time this model makes a melee attack that targets a unit that is below its Starting Strength, add 1 to the Hit roll. If that target is also Below Half-strength, add 1 to the Wound roll as well."
    },
    "tags": ["Monster", "Great Devourer", "Psychophage", "Tyranids"],
    "models": {
      "Psychophage": [1, 1]
    },
    "equipment": ["Psychoclastic Torrent", "Talons and Betentacled Maw"]
  },

  {
    "name": "Barbgaunts",
    "points": [50, 100],
    "stats": {
      "movement": 6,
      "toughness": 4,
      "save": 4,
      "invulnerable": 7,
      "wounds": 2,
      "leadership": 8,
      "objective_control": 1
    },
    "weapons": [
      {
        "name": "Bio-Cannon",
        "range": 24,
        "attacks": 0,
        "attack_dice": "d6",
        "hit": 4,
        "strength": 5,
        "armour_pen": 0,
        "damage": 1,
        "tags": ["Blast", "Heavy"],
        "ranged": true
      },
      {
        "name": "Xenos claws and teeth",
        "range": 0,
        "attacks": 1,
        "hit": 4,
        "strength": 4,
        "armour_pen": 0,
        "damage": 1,
        "tags": [],
        "ranged": false
      }
    ],
    "abilities": {
      "synapse": false,
      "Disruption Bombardment": "In your Shooting phase, after this unit has shot, if an enemy Infantry unit was hit by one or more of those attacks made by this unit’s bio-cannons, until the end of your opponent’s next turn, that enemy unit is disrupted. While a unit is disrupted, subtract 2 from its Move characteristic, and subtract 2 from Advance and Charge rolls made for it."
    },
    "tags": ["Infantry", "Great Devourer", "Barbgaunts", "Tyranids"],
    "models": {
      "Barbgaunts": [5, 10]
    },
    "equipment": ["Bio-Cannon", "Xenos claws and teeth"]
  }
]
